README.md
setup.py
aiopaybear/__init__.py
aiopaybear.egg-info/PKG-INFO
aiopaybear.egg-info/SOURCES.txt
aiopaybear.egg-info/dependency_links.txt
aiopaybear.egg-info/requires.txt
aiopaybear.egg-info/top_level.txt