Metadata-Version: 2.1
Name: aiopaybear
Version: 0.1.1
Summary: Async paybear.io/savvy.io client
Home-page: https://github.com/omarryhan/aiopaybear
Author: Omar Ryhan
Author-email: omarryhan@gmail.com
License: GNU
Platform: UNKNOWN
Classifier: Programming Language :: Python :: 3.7
Classifier: Operating System :: OS Independent
